README.rst
setup.py
memory_time_tracker/__init__.py
memory_time_tracker/__version__.py
memory_time_tracker/get_refresh_delay.py
memory_time_tracker/get_used_ram.py
memory_time_tracker/plot.py
memory_time_tracker/resources_logger.py
memory_time_tracker/tracker.py
memory_time_tracker/utils.py
memory_time_tracker.egg-info/PKG-INFO
memory_time_tracker.egg-info/SOURCES.txt
memory_time_tracker.egg-info/dependency_links.txt
memory_time_tracker.egg-info/requires.txt
memory_time_tracker.egg-info/top_level.txt