Metadata-Version: 1.2
Name: memory-time-tracker
Version: 0.0.5
Summary: Python tool to track the memory and time requirements of software.
Home-page: https://github.com/LucaCappelletti94/memory_time_tracker
Author: Luca Cappelletti, Tommaso Fontana
Author-email: cappelletti.luca94@gmail.com, tommaso.fontana.96@gmail.com
License: MIT
Platform: UNKNOWN
Requires-Python: >=3.6.0
